PyMacroFin/__init__.py
PyMacroFin/dash_utils.py
PyMacroFin/engine.py
PyMacroFin/equation.py
PyMacroFin/grid.py
PyMacroFin/innerloop.py
PyMacroFin/kolmogorov.py
PyMacroFin/model.py
PyMacroFin/outerloop.py
PyMacroFin/parameters.py
PyMacroFin/stencil_decomposition.py
PyMacroFin/system.py
PyMacroFin/utilities.py
PyMacroFin-0.0.1.2.dist-info/LICENSE.txt
PyMacroFin-0.0.1.2.dist-info/METADATA
PyMacroFin-0.0.1.2.dist-info/WHEEL
PyMacroFin-0.0.1.2.dist-info/top_level.txt
PyMacroFin-0.0.1.2.dist-info/RECORD
